xgovuk_flask_admin/__init__.py
xgovuk_flask_admin/assets.py
xgovuk_flask_admin/fields.py
xgovuk_flask_admin/filters.py
xgovuk_flask_admin/pagination.py
xgovuk_flask_admin/theme.py
xgovuk_flask_admin/utils.py
xgovuk_flask_admin/widgets.py
xgovuk_flask_admin/templates/datetime-input.html
xgovuk_flask_admin/templates/select-with-search.html
xgovuk_flask_admin/templates/admin/actions.html
xgovuk_flask_admin/templates/admin/base.html
xgovuk_flask_admin/templates/admin/index.html
xgovuk_flask_admin/templates/admin/layout.html
xgovuk_flask_admin/templates/admin/lib.html
xgovuk_flask_admin/templates/admin/master.html
xgovuk_flask_admin/templates/admin/static.html
xgovuk_flask_admin/templates/admin/model/create.html
xgovuk_flask_admin/templates/admin/model/details.html
xgovuk_flask_admin/templates/admin/model/edit.html
xgovuk_flask_admin/templates/admin/model/inline_field_list.html
xgovuk_flask_admin/templates/admin/model/inline_form.html
xgovuk_flask_admin/templates/admin/model/inline_list_base.html
xgovuk_flask_admin/templates/admin/model/layout.html
xgovuk_flask_admin/templates/admin/model/list.html
xgovuk_flask_admin/templates/admin/model/row_actions.html
xgovuk_flask_admin/static/dist/manifest.json
xgovuk_flask_admin/static/dist/assets/main-CywrudZx.css
xgovuk_flask_admin/static/dist/assets/main-DXgl75mv.js
xgovuk_flask_admin/static/dist/assets/manifest.json
xgovuk_flask_admin/static/dist/assets/fonts/bold-affa96571d-v2.woff
xgovuk_flask_admin/static/dist/assets/fonts/bold-b542beb274-v2.woff2
xgovuk_flask_admin/static/dist/assets/fonts/light-94a07e06a1-v2.woff2
xgovuk_flask_admin/static/dist/assets/fonts/light-f591b13f7d-v2.woff
xgovuk_flask_admin/static/dist/assets/images/favicon.ico
xgovuk_flask_admin/static/dist/assets/images/favicon.svg
xgovuk_flask_admin/static/dist/assets/images/govuk-crest.svg
xgovuk_flask_admin/static/dist/assets/images/govuk-icon-180.png
xgovuk_flask_admin/static/dist/assets/images/govuk-icon-192.png
xgovuk_flask_admin-0.1.7.dist-info/METADATA
xgovuk_flask_admin-0.1.7.dist-info/WHEEL
xgovuk_flask_admin-0.1.7.dist-info/RECORD
