Metadata-Version: 2.4
Name: xgovuk-flask-admin
Version: 0.1.7
Summary: Add your description here
Requires-Python: >=3.12
Requires-Dist: beautifulsoup4>=4.14.2
Requires-Dist: email-validator>=2.0.0
Requires-Dist: flask-admin>=2.0.0rc1
Requires-Dist: flask>=3
Requires-Dist: govuk-frontend-jinja==3.10.0
Requires-Dist: govuk-frontend-wtf==3.2.0
Requires-Dist: markupsafe>=3.0.0
Requires-Dist: sqlalchemy>2
Requires-Dist: tox-uv>=1.29.0
